hoverxref/__init__.py
hoverxref/domains.py
hoverxref/extension.py
hoverxref/_static/css/alabaster.css
hoverxref/_static/css/micromodal.css
hoverxref/_static/css/sphinx_material.css
hoverxref/_static/css/sphinx_rtd_theme.css
hoverxref/_static/css/tooltipster-sideTip-borderless.min.css
hoverxref/_static/css/tooltipster-sideTip-light.min.css
hoverxref/_static/css/tooltipster-sideTip-noir.min.css
hoverxref/_static/css/tooltipster-sideTip-punk.min.css
hoverxref/_static/css/tooltipster-sideTip-shadow.min.css
hoverxref/_static/css/tooltipster.bundle.min.css
hoverxref/_static/css/tooltipster.custom.css_t
hoverxref/_static/js/hoverxref.js_t
hoverxref/_static/js/micromodal.min.js
hoverxref/_static/js/tooltipster.bundle.min.js
sphinx_hoverxref-1.4.2.dist-info/LICENSE
sphinx_hoverxref-1.4.2.dist-info/WHEEL
sphinx_hoverxref-1.4.2.dist-info/METADATA
sphinx_hoverxref-1.4.2.dist-info/RECORD
