Metadata-Version: 2.3
Name: sphinx-hoverxref
Version: 1.4.2
Summary: Sphinx extension to show tooltips with content embedded when hover a reference.
Keywords: tooltip,modal,hover,hoverxref,sphinx,documentation
Author-email: Manuel Kaufmann <humitos@gmail.com>
Classifier: Development Status :: 5 - Production/Stable
Classifier: Framework :: Sphinx
Classifier: Framework :: Sphinx :: Extension
Classifier: License :: OSI Approved :: MIT License
Classifier: Operating System :: OS Independent
Classifier: Programming Language :: Python :: 2.7
Classifier: Programming Language :: Python :: 3
Classifier: Topic :: Documentation :: Sphinx
Classifier: Topic :: Software Development :: Documentation
Requires-Dist: sphinx >=5.0
Requires-Dist: sphinxcontrib-jquery
Requires-Dist: sphinx ; extra == "doc"
Requires-Dist: sphinx-autoapi ; extra == "doc"
Requires-Dist: sphinx-rtd-theme ; extra == "doc"
Requires-Dist: sphinx-tabs ; extra == "doc"
Requires-Dist: sphinx-prompt ; extra == "doc"
Requires-Dist: sphinx-version-warning ; extra == "doc"
Requires-Dist: sphinx-notfound-page ; extra == "doc"
Requires-Dist: sphinx-autobuild ; extra == "doc"
Requires-Dist: sphinxcontrib-bibtex>=2.6.0 ; extra == "doc"
Requires-Dist: sphinxemoji ; extra == "doc"
Requires-Dist: tox ; extra == "test"
Project-URL: Documentation, https://sphinx-hoverxref.readthedocs.io/
Project-URL: Source, https://github.com/readthedocs/sphinx-hoverxref
Project-URL: Tracker, https://github.com/readthedocs/sphinx-hoverxref/issues
Provides-Extra: doc
Provides-Extra: test
